kgisuperpy-1.0.4.dist-info/licenses/LICENSE
superpy/DT.py
superpy/IntelligencePy.py
superpy/PackagePy.py
superpy/__init__.py
superpy/account.py
superpy/constant.py
superpy/contracts.py
superpy/order.py
superpy/quote.py
superpy/report.py
superpy/stream_data_type.py
superpy/superpy.py
superpy/.libs/ICSharpCode.SharpZipLib.dll
superpy/.libs/Interop.KGICGCAPIATLLib.dll
superpy/.libs/Package.dll
superpy/.libs/PushClient.dll
superpy/.libs/QuoteCom.dll
superpy/.libs/TradeCom.dll
superpy/QuoteCom/Future.py
superpy/QuoteCom/Login.py
superpy/QuoteCom/Stock.py
superpy/QuoteCom/__init__.py
superpy/TradeCom/Login.py
superpy/TradeCom/__init__.py
superpy/TradeCom/Future/Order.py
superpy/TradeCom/Future/Report.py
superpy/TradeCom/Future/__init__.py
superpy/TradeCom/Stock/Order.py
superpy/TradeCom/Stock/Report.py
superpy/TradeCom/Stock/__init__.py
kgisuperpy-1.0.4.dist-info/METADATA
kgisuperpy-1.0.4.dist-info/WHEEL
kgisuperpy-1.0.4.dist-info/top_level.txt
kgisuperpy-1.0.4.dist-info/RECORD
