Metadata-Version: 2.4
Name: kgisuperpy
Version: 1.0.4
Summary: KGI project
Author: KGI Securities
Author-email: ec.service@kgi.com
License-File: LICENSE
Requires-Dist: pythonnet
Dynamic: author
Dynamic: author-email
Dynamic: description
Dynamic: description-content-type
Dynamic: license-file
Dynamic: requires-dist
Dynamic: summary
